topsis_sanjana_102103040
