Metadata-Version: 2.1
Name: topsis_sanjana_102103040
Version: 0.5
Summary: Topsis Package
Author: Sanjana Sinha
Author-email: sanjanasinha171@gmail.com
License: MIT
Keywords: TOPSIS,MCDM
Classifier: Development Status :: 3 - Alpha
Classifier: Intended Audience :: Developers
Classifier: Topic :: Software Development :: Build Tools
Classifier: License :: OSI Approved :: MIT License
Classifier: Programming Language :: Python :: 3
License-File: LICENSE.txt
Requires-Dist: numpy
Requires-Dist: pandas
